<annotation>
	<filename>32191.jpg</filename>
	<size>
		<width>1280</width>
		<height>720</height>
		<depth>3</depth>
	</size>
	<object>
		<name>weed</name>
		<bndbox>
			<xmin>786</xmin>
			<ymin>288</ymin>
			<xmax>830</xmax>
			<ymax>311</ymax>
		</bndbox>
	</object>
	<object>
		<name>weed</name>
		<bndbox>
			<xmin>1041</xmin>
			<ymin>138</ymin>
			<xmax>1085</xmax>
			<ymax>160</ymax>
		</bndbox>
	</object>
	<object>
		<name>weed</name>
		<bndbox>
			<xmin>1171</xmin>
			<ymin>335</ymin>
			<xmax>1195</xmax>
			<ymax>366</ymax>
		</bndbox>
	</object>
	<object>
		<name>weed</name>
		<bndbox>
			<xmin>1209</xmin>
			<ymin>280</ymin>
			<xmax>1235</xmax>
			<ymax>324</ymax>
		</bndbox>
	</object>
	<object>
		<name>weed</name>
		<bndbox>
			<xmin>317</xmin>
			<ymin>294</ymin>
			<xmax>379</xmax>
			<ymax>331</ymax>
		</bndbox>
	</object>
	<object>
		<name>weed</name>
		<bndbox>
			<xmin>423</xmin>
			<ymin>559</ymin>
			<xmax>461</xmax>
			<ymax>601</ymax>
		</bndbox>
	</object>
	<object>
		<name>weed</name>
		<bndbox>
			<xmin>868</xmin>
			<ymin>574</ymin>
			<xmax>897</xmax>
			<ymax>617</ymax>
		</bndbox>
	</object>
	<object>
		<name>weed</name>
		<bndbox>
			<xmin>1121</xmin>
			<ymin>499</ymin>
			<xmax>1152</xmax>
			<ymax>523</ymax>
		</bndbox>
	</object>
	<object>
		<name>weed</name>
		<bndbox>
			<xmin>491</xmin>
			<ymin>125</ymin>
			<xmax>523</xmax>
			<ymax>149</ymax>
		</bndbox>
	</object>
	<object>
		<name>weed</name>
		<bndbox>
			<xmin>119</xmin>
			<ymin>205</ymin>
			<xmax>165</xmax>
			<ymax>235</ymax>
		</bndbox>
	</object>
	<object>
		<name>weed</name>
		<bndbox>
			<xmin>178</xmin>
			<ymin>133</ymin>
			<xmax>220</xmax>
			<ymax>168</ymax>
		</bndbox>
	</object>
	<object>
		<name>weed</name>
		<bndbox>
			<xmin>373</xmin>
			<ymin>152</ymin>
			<xmax>398</xmax>
			<ymax>169</ymax>
		</bndbox>
	</object>
	<object>
		<name>weed</name>
		<bndbox>
			<xmin>931</xmin>
			<ymin>465</ymin>
			<xmax>944</xmax>
			<ymax>491</ymax>
		</bndbox>
	</object>
</annotation>